migrations/__init__.py
django_error_alert-0.1.0.dist-info/METADATA
django_error_alert-0.1.0.dist-info/WHEEL
django_error_alert-0.1.0.dist-info/top_level.txt
django_error_alert-0.1.0.dist-info/RECORD
